{
  "itemrelease": {
    "version": "2.0",
    "item": {
      "format": "nl",
      "id": "1507",
      "version": "8",
      "bankkey": "187",
      "associatedpassage": "3694",
      "attriblist": {
        "attrib": [
          {
            "attid": "itm_item_id",
            "name": "Item: ITS ID",
            "val": "1507"
          },
          {
            "attid": "itm_item_subject",
            "name": "Item: Subject",
            "val": "MATH"
          },
          {
            "attid": "itm_item_desc",
            "name": "Item: Item Description",
            "val": "MA08_PT_HTBEAT_Q3"
          },
          {
            "attid": "itm_FTUse",
            "name": "Fieldtest Use",
            "val": "PracTest::MG8::Perf::SP13 (3); PracTest::MG8::Perf::SP13::BRAILLE (3); PracTest::MG8::Perf::SP13::ENU::Refresh (3); PracTest::MG8::Perf::SP13::BRL::Refresh (3); PracTest::MG8::Perf::SP13::ESN::Refresh (3);"
          },
          {
            "attid": "itm_OPUse",
            "name": "Operational Use"
          },
          {
            "attid": "itm_att_Answer Key",
            "name": "Item: Answer Key",
            "val": "NL"
          },
          {
            "attid": "itm_att_Grade",
            "name": "Item: Grade",
            "val": "8",
            "desc": "8"
          },
          {
            "attid": "itm_att_Item Format",
            "name": "Item: Item Format",
            "val": "NL",
            "desc": "NL [3]"
          },
          {
            "attid": "itm_att_Page Layout",
            "name": "Item: Page Layout",
            "val": "21"
          },
          {
            "attid": "itm_att_Response Type",
            "name": "Item: Response Type",
            "val": "PlainText"
          },
          {
            "attid": "itm_att_Item Point",
            "name": "Item: Item Point",
            "val": "2 pts.",
            "desc": "2 Points"
          },
          {
            "attid": "stm_pass_id",
            "name": "Stim: ITS ID",
            "val": "3694"
          }
        ]
      },
      "tutorial": {
        "id": "1078",
        "bankkey": "187"
      },
      "resourceslist": {
        "resource": {
          "type": "wordList",
          "id": "1635",
          "index": "1",
          "bankkey": "187"
        }
      },
      "MachineRubric": { "filename": "Item_1507_v8.nlx" },
      "content": [
        {
          "language": "ENU",
          "version": "2.0",
          "approvedVersion": "8",
          "stem": "<p style=\"\">Interpret the slope of the line from <span id=\"item_1507_TAG_1_BEGIN\">Item 1</span> in the <span id=\"item_1507_TAG_4\" class=\"its-tag\" data-tag=\"word\" data-tag-boundary=\"start\" data-word-index=\"1\"></span>context<span class=\"its-tag\" data-tag-ref=\"item_1507_TAG_4\" data-tag-boundary=\"end\"></span> of the <span id=\"item_1507_TAG_5\" class=\"its-tag\" data-tag=\"word\" data-tag-boundary=\"start\" data-word-index=\"2\"></span>situation<span class=\"its-tag\" data-tag-ref=\"item_1507_TAG_5\" data-tag-boundary=\"end\"></span>.</p><p style=\"\">&#xA0;</p><p style=\"\"><span id=\"item_1507_TAG_6\" class=\"its-tag\" data-tag=\"word\" data-tag-boundary=\"start\" data-word-index=\"3\"></span>Type<span class=\"its-tag\" data-tag-ref=\"item_1507_TAG_6\" data-tag-boundary=\"end\"></span> your answer in the <span id=\"item_1507_TAG_7\" class=\"its-tag\" data-tag=\"word\" data-tag-boundary=\"start\" data-word-index=\"4\"></span>space provided<span class=\"its-tag\" data-tag-ref=\"item_1507_TAG_7\" data-tag-boundary=\"end\"></span><span style=\"font-weight:normal; \">.</span> </p>",
          "rubriclist": {
            "rubric": [
              {
                "scorepoint": "2",
                "name": "Rubric 2",
                "val": "<p style=\"\">Sample Response: There is a 0.11 decrease in average pulse rate for every 1kg increase in animal weight.</p><p style=\"\">Award 2 points if response includes:</p><p style=\"\">&#xA0;</p><ul style=\"padding-left:1.5000em; \"><li><p style=\"\">The correct pulse rate and weight</p><p style=\"\">AND</p></li><li><p style=\"\">“for every 1kg” language.</p></li></ul><p style=\"\">&#xA0;</p>"
              },
              {
                "scorepoint": "1",
                "name": "Rubric 1",
                "val": "<p style=\"\">Award 1 point if response includes:</p><p style=\"\">&#xA0;</p><ul style=\"padding-left:1.5000em; \"><li><p style=\"\">The correct pulse rate and weight</p><p style=\"\">OR</p></li><li><p style=\"\">“for every 1kg” language.</p></li></ul><p style=\"\">&#xA0;</p>"
              },
              {
                "scorepoint": "0",
                "name": "Rubric 0",
                "val": "<p style=\"\">The response does not meet the criteria required to earn one point. The response indicates inadequate or no understanding of the task and/or the idea or concept needed to answer the item. It may only repeat information given in the test item. The response may provide an incorrect solution/response and the provided supportive information may be irrelevant to the item, or possibly, no other information is shown. The student may have written on a different topic or written, “I don't know.”</p>"
              }
            ],
            "samplelist": [
              {
                "maxval": "2",
                "minval": "2",
                "sample": {
                  "purpose": "OtherExemplar",
                  "scorepoint": "2",
                  "name": "2-Point Other Official Sample Answers",
                  "samplecontent": "<p style=\"\">NA</p>"
                }
              },
              {
                "maxval": "1",
                "minval": "1",
                "sample": {
                  "purpose": "Exemplar",
                  "scorepoint": "1",
                  "name": "1-Point Official Sample Answer",
                  "samplecontent": "<p style=\"\">NA</p>"
                }
              },
              {
                "maxval": "0",
                "minval": "0",
                "sample": {
                  "purpose": "Exemplar",
                  "scorepoint": "0",
                  "name": "0-Point Official Sample Answer",
                  "samplecontent": "<p style=\"\">NA</p>"
                }
              }
            ]
          },
          "attachmentlist": {
            "attachment": [
              {
                "id": "braillefile1",
                "type": "BRF",
                "subtype": "nemeth",
                "file": "item_1507_enu_nemeth.brf"
              },
              {
                "pass": "true",
                "id": "aslfile1",
                "type": "ASL",
                "subtype": "STEM",
                "file": "item_1507_ASL_STEM.MP4"
              }
            ]
          },
          "apipAccessibility": {
            "accessibilityInfo": {
              "accessElement": {
                "identifier": "ae1",
                "contentLinkInfo": {
                  "itsLinkIdentifierRef": "item_1507_TAG_1_BEGIN",
                  "type": "Text"
                },
                "relatedElementInfo": {
                  "readAloud": {
                    "textToSpeechPronunciation": "Item 1,",
                    "textToSpeechPronunciationAlternate": "Item 1"
                  },
                  "brailleText": { "brailleTextString": "Item 1" }
                }
              }
            }
          }
        },
        {
          "language": "ESN",
          "version": "2.0",
          "approvedVersion": "8",
          "stem": "<p style=\"\">Interpreta la pendiente de la línea de la pregunta 1 dentro del contexto de la situación.</p><p style=\"\">&#xA0;</p><p style=\"\">Escribe tu respuesta en el espacio provisto<span style=\"font-weight:normal; \">.</span></p><p class=\"languagedivider\">&#xA0;</p><p style=\"\">Interpret the slope of the line from <span id=\"item_1507_TAG_1_BEGIN\">Item 1</span> in the <span id=\"item_1507_TAG_4\" class=\"its-tag\" data-tag=\"word\" data-tag-boundary=\"start\" data-word-index=\"1\"></span>context<span class=\"its-tag\" data-tag-ref=\"item_1507_TAG_4\" data-tag-boundary=\"end\"></span> of the <span id=\"item_1507_TAG_5\" class=\"its-tag\" data-tag=\"word\" data-tag-boundary=\"start\" data-word-index=\"2\"></span>situation<span class=\"its-tag\" data-tag-ref=\"item_1507_TAG_5\" data-tag-boundary=\"end\"></span>.</p><p style=\"\">&#xA0;</p><p style=\"\"><span id=\"item_1507_TAG_6\" class=\"its-tag\" data-tag=\"word\" data-tag-boundary=\"start\" data-word-index=\"3\"></span>Type<span class=\"its-tag\" data-tag-ref=\"item_1507_TAG_6\" data-tag-boundary=\"end\"></span> your answer in the <span id=\"item_1507_TAG_7\" class=\"its-tag\" data-tag=\"word\" data-tag-boundary=\"start\" data-word-index=\"4\"></span>space provided<span class=\"its-tag\" data-tag-ref=\"item_1507_TAG_7\" data-tag-boundary=\"end\"></span><span style=\"font-weight:normal; \">.</span> </p>",
          "apipAccessibility": {
            "accessibilityInfo": {
              "accessElement": {
                "identifier": "ae1",
                "contentLinkInfo": {
                  "itsLinkIdentifierRef": "item_1507_TAG_1_BEGIN",
                  "type": "Text"
                },
                "relatedElementInfo": {
                  "readAloud": {
                    "textToSpeechPronunciation": "Item 1,",
                    "textToSpeechPronunciationAlternate": "Item 1"
                  },
                  "brailleText": { "brailleTextString": "Item 1" }
                }
              }
            }
          }
        }
      ]
    }
  }
}

